LICENSE
MANIFEST.in
README.md
setup.cfg
setup.py
tests/integration/__init__.py
tests/unit/__init__.py
tests/unit/resources.py
tests/unit/test_api_client.py
tests/unit/test_trustar.py
tests/unit/handlers/__init__.py
tests/unit/handlers/test_account.py
tests/unit/handlers/test_indicators.py
tests/unit/handlers/test_observables_handler.py
tests/unit/handlers/test_safelist.py
tests/unit/handlers/test_search_handler.py
tests/unit/handlers/test_submission.py
tests/unit/handlers/test_tags.py
tests/unit/handlers/test_workflow.py
tests/unit/models/__init__.py
tests/unit/models/test_enclave.py
tests/unit/models/test_indicator.py
tests/unit/models/test_prioritized_indicator.py
tests/unit/models/test_safelists.py
tests/unit/models/test_searched_observable.py
tests/unit/models/test_searched_submission.py
tests/unit/models/test_workflow_configs.py
tests/unit/models/test_workflow_model.py
trustar2/__init__.py
trustar2/api_client.py
trustar2/base.py
trustar2/config.py
trustar2/log.py
trustar2/query.py
trustar2/trustar.py
trustar2/trustar_enums.py
trustar2/version.py
trustar2.egg-info/PKG-INFO
trustar2.egg-info/SOURCES.txt
trustar2.egg-info/dependency_links.txt
trustar2.egg-info/requires.txt
trustar2.egg-info/top_level.txt
trustar2/handlers/__init__.py
trustar2/handlers/account.py
trustar2/handlers/base_handler.py
trustar2/handlers/indicators.py
trustar2/handlers/observables.py
trustar2/handlers/safelist.py
trustar2/handlers/search_handler.py
trustar2/handlers/submission.py
trustar2/handlers/tags.py
trustar2/handlers/workflow.py
trustar2/models/__init__.py
trustar2/models/base.py
trustar2/models/enclave.py
trustar2/models/entity.py
trustar2/models/indicator.py
trustar2/models/prioritized_indicator.py
trustar2/models/safelists.py
trustar2/models/score_context.py
trustar2/models/searched_observable.py
trustar2/models/searched_submission.py
trustar2/models/submission_details.py
trustar2/models/trustar_response.py
trustar2/models/workflow.py
trustar2/models/workflow_configs.py