Metadata-Version: 1.1
Name: trustar2
Version: 0.7.1
Summary: Python SDK2 for the TruSTAR REST API
Home-page: https://github.com/trustar/trustar-sdk2-proto/
Author: TruSTAR Technology, Inc.
Author-email: support@trustar.co
License: MIT
Download-URL: https://github.com/trustar/trustar-sdk2-proto/tarball/0.7.1
Platform: UNKNOWN
